jsonly/__init__.py
jsonly/client.py
jsonly/connect.py
jsonly/convert.py
jsonly/error.py
jsonly-2.0.2.dist-info/LICENSE
jsonly-2.0.2.dist-info/METADATA
jsonly-2.0.2.dist-info/WHEEL
jsonly-2.0.2.dist-info/top_level.txt
jsonly-2.0.2.dist-info/RECORD
