Metadata-Version: 2.1
Name: jsonly
Version: 2.0.2
Summary: JSON 데이터 관리 라이브러리
Home-page: https://github.com/VoidAsMad/jsonly
Author: VoidAsMad
Author-email: star@devksy.xyz
License: MIT
Requires-Python: >=3.10
License-File: LICENSE
